Conolist-0.20.data/scripts/__init__.py
conolist/__init__.py
conolist/command_line.py
Conolist-0.20.dist-info/LICENSE
Conolist-0.20.dist-info/METADATA
Conolist-0.20.dist-info/WHEEL
Conolist-0.20.dist-info/entry_points.txt
Conolist-0.20.dist-info/top_level.txt
Conolist-0.20.dist-info/RECORD
