Metadata-Version: 2.1
Name: Conolist
Version: 0.20
Summary: Surf paths easily from console.
Home-page: https://github.com/E-RROR/conolist
Author: Sina Farhadi
Author-email: sina.farhadi.cyber@gmail.com
License: MIT
Platform: UNKNOWN
Classifier: Operating System :: OS Independent
Classifier: Programming Language :: Python
Classifier: Programming Language :: Python :: 3
Classifier: Programming Language :: Python :: 3 :: Only
Classifier: Programming Language :: Python :: 3.6
Classifier: Programming Language :: Python :: 3.7
Classifier: Programming Language :: Python :: 3.8
Requires-Python: >=3
